pncl/__init__.py
pncl/plots.py
pncl/plotter.py
pncl/server.py
pncl/utils.py
pncl/static/favicon.ico
pncl/static/index.html
pncl/static/main.js
pncl/static/style.css
pncl-1.0.0.dist-info/LICENSE
pncl-1.0.0.dist-info/METADATA
pncl-1.0.0.dist-info/WHEEL
pncl-1.0.0.dist-info/top_level.txt
pncl-1.0.0.dist-info/RECORD
