Metadata-Version: 2.1
Name: pncl
Version: 1.0.0
Summary: UNKNOWN
Home-page: https://github.com/danielegrattarola/pncl
Author: Daniele Grattarola
Author-email: daniele.grattarola@gmail.com
License: MIT
Platform: UNKNOWN
Classifier: Programming Language :: Python :: 3.6
Requires-Dist: aiohttp
Requires-Dist: aiohttp-sse
Requires-Dist: numpy
Requires-Dist: requests
